purediffusion/__init__.py
purediffusion/cold.py
purediffusion/dataset.py
purediffusion/gaussian.py
purediffusion/model.py
purediffusion/optimization.py
purediffusion-0.1.1.dist-info/LICENSE
purediffusion-0.1.1.dist-info/METADATA
purediffusion-0.1.1.dist-info/WHEEL
purediffusion-0.1.1.dist-info/top_level.txt
purediffusion-0.1.1.dist-info/RECORD
